{
  "fill-specializations" : [
    {
      "value" : {
        "solid" : "display-p3:0.48849,0.43312,0.99697,1.00000"
      }
    },
    {
      "appearance" : "dark",
      "value" : "automatic"
    }
  ],
  "groups" : [
    {
      "blur-material" : null,
      "layers" : [
        {
          "blend-mode" : "normal",
          "fill-specializations" : [
            {
              "value" : {
                "automatic-gradient" : "srgb:1.00000,1.00000,1.00000,1.00000"
              }
            },
            {
              "appearance" : "dark",
              "value" : {
                "solid" : "srgb:1.00000,1.00000,1.00000,1.00000"
              }
            },
            {
              "appearance" : "tinted",
              "value" : {
                "solid" : "extended-gray:1.00000,1.00000"
              }
            }
          ],
          "glass" : true,
          "image-name" : "safe.svg",
          "name" : "safe",
          "position" : {
            "scale" : 2,
            "translation-in-points" : [
              9.6953125,
              -3
            ]
          }
        }
      ],
      "shadow" : {
        "kind" : "neutral",
        "opacity" : 0.5
      },
      "translucency" : {
        "enabled" : true,
        "value" : 0.5
      }
    }
  ],
  "supported-platforms" : {
    "circles" : [
      "watchOS"
    ],
    "squares" : "shared"
  }
}